bq_iterate/__init__.py
bq_iterate/config.py
bq_iterate/core.py
bq_iterate/retry.py
bq_iterate/utils.py
bq_iterate-0.1.7.dist-info/LICENSE
bq_iterate-0.1.7.dist-info/WHEEL
bq_iterate-0.1.7.dist-info/METADATA
bq_iterate-0.1.7.dist-info/RECORD
