Metadata-Version: 2.1
Name: bq-iterate
Version: 0.1.7
Summary: Work with BigQuery data as you do with lists in python
Home-page: https://github.com/Senhaji-Rhazi-Hamza/bq_iterate
License: MIT
Keywords: BigQuery,google,batch,gcp
Author: Senhaji-Rhazi-Hamza
Author-email: hamza.senhajirhazi@gmal.com
Requires-Python: >=3.8
Classifier: License :: OSI Approved :: MIT License
Classifier: Programming Language :: Python :: 3
Classifier: Programming Language :: Python :: 3.10
Classifier: Programming Language :: Python :: 3.8
Classifier: Programming Language :: Python :: 3.9
Requires-Dist: google-cloud-bigquery (>=2.2.0,<3.0.0)
Requires-Dist: tenacity (>=7.0.0,<8.0.0)
Project-URL: Repository, https://github.com/Senhaji-Rhazi-Hamza/bq_iterate
